randompassword_generator.py
randompassword_generator-1.0.dist-info/METADATA
randompassword_generator-1.0.dist-info/WHEEL
randompassword_generator-1.0.dist-info/top_level.txt
randompassword_generator-1.0.dist-info/RECORD
