Metadata-Version: 2.1
Name: randompassword-generator
Version: 1.0
Summary: A package that generates random passwords. 
Home-page: https://github.com/shyamgopal01/randompassword_generator
Author: Shyam Gopal , Venkateswar.S
Author-email: shyamgopalit@gmail.com
License: UNKNOWN
Platform: UNKNOWN
Classifier: Programming Language :: Python :: 3.5
Classifier: Programming Language :: Python :: 3.6
Classifier: Programming Language :: Python :: 3.7
Classifier: Programming Language :: Python :: 3.8
Classifier: Operating System :: OS Independent
Requires-Dist: random
Requires-Dist: array
